{
  "district": "fin",
  "year": 2021,
  "events": [
    {
      "key": "202121fin",
      "name": "2021 Season Participation for FIN District Teams",
      "startDate": "2021-03-01",
      "teams": [
        1018,
        1024,
        135,
        1501,
        1529,
        1555,
        1646,
        1720,
        1741,
        1747,
        2171,
        2197,
        234,
        2867,
        2909,
        292,
        3147,
        3176,
        3180,
        3487,
        3494,
        3559,
        3865,
        3936,
        3940,
        3947,
        4272,
        447,
        4485,
        45,
        4580,
        461,
        4926,
        4982,
        5010,
        5188,
        5402,
        5484,
        6451,
        6498,
        6721,
        6956,
        71,
        7198,
        7454,
        7457,
        7477,
        7617,
        7657,
        7695,
        8103,
        8116,
        8232,
        829,
        8535,
        8545,
        8564,
        868
      ]
    }
  ],
  "teams": {
    "45": {
      "name": "TechnoKats Robotics Team",
      "rookie_year": 1992
    },
    "71": {
      "name": "Team Hammond",
      "rookie_year": 1996
    },
    "135": {
      "name": "Penn Robotics Black Knights",
      "rookie_year": 1998
    },
    "234": {
      "name": "Cyber Blue",
      "rookie_year": 1999
    },
    "292": {
      "name": "PantherTech",
      "rookie_year": 1999
    },
    "447": {
      "name": "Team Roboto",
      "rookie_year": 2000
    },
    "461": {
      "name": "Westside Boiler Invasion",
      "rookie_year": 2000
    },
    "829": {
      "name": "The Digital Goats",
      "rookie_year": 2002
    },
    "868": {
      "name": "TechHOUNDS",
      "rookie_year": 2002
    },
    "1018": {
      "name": "Pike RoboDevils",
      "rookie_year": 2003
    },
    "1024": {
      "name": "Kil-A-Bytes",
      "rookie_year": 2003
    },
    "1501": {
      "name": "Team THRUST",
      "rookie_year": 2005
    },
    "1529": {
      "name": "CyberCards",
      "rookie_year": 2005
    },
    "1555": {
      "name": "CryoFrost",
      "rookie_year": 2005
    },
    "1646": {
      "name": "Precision Guessworks",
      "rookie_year": 2005
    },
    "1720": {
      "name": "PhyXTGears",
      "rookie_year": 2006
    },
    "1741": {
      "name": "Red Alert",
      "rookie_year": 2006
    },
    "1747": {
      "name": "Harrison Boiler Robotics",
      "rookie_year": 2006
    },
    "2171": {
      "name": "RoboDogs",
      "rookie_year": 2007
    },
    "2197": {
      "name": "Las Pumas",
      "rookie_year": 2007
    },
    "2867": {
      "name": "ElkLogics",
      "rookie_year": 2009
    },
    "2909": {
      "name": "Zebra Bots",
      "rookie_year": 2009
    },
    "3147": {
      "name": "Munster Horsepower",
      "rookie_year": 2010
    },
    "3176": {
      "name": "Purple Precision",
      "rookie_year": 2010
    },
    "3180": {
      "name": "MECHAlosaurs",
      "rookie_year": 2010
    },
    "3487": {
      "name": "Red Pride Robotics",
      "rookie_year": 2011
    },
    "3494": {
      "name": "The Quadrangles",
      "rookie_year": 2011
    },
    "3559": {
      "name": "Thundercats",
      "rookie_year": 2011
    },
    "3865": {
      "name": "Riley WildBots",
      "rookie_year": 2011
    },
    "3936": {
      "name": "RoboBlitz 3936",
      "rookie_year": 2012
    },
    "3940": {
      "name": "CyberTooth",
      "rookie_year": 2012
    },
    "3947": {
      "name": "The Last Crusaders",
      "rookie_year": 2012
    },
    "4272": {
      "name": "Maverick Robotics",
      "rookie_year": 2012
    },
    "4485": {
      "name": "Tribe Tech Robotics",
      "rookie_year": 2013
    },
    "4580": {
      "name": "Conductors",
      "rookie_year": 2013
    },
    "4926": {
      "name": "GalacTech",
      "rookie_year": 2014
    },
    "4982": {
      "name": "Olympus Robotics",
      "rookie_year": 2014
    },
    "5010": {
      "name": "Tiger Dynasty",
      "rookie_year": 2014
    },
    "5188": {
      "name": "Area 5188: Classified Robotics",
      "rookie_year": 2014
    },
    "5402": {
      "name": "Wreckless Robotics",
      "rookie_year": 2015
    },
    "5484": {
      "name": "Career Academy Robotics - Wolf Pack",
      "rookie_year": 2015
    },
    "6451": {
      "name": "Wired Warriors",
      "rookie_year": 2017
    },
    "6498": {
      "name": "Castle Robotics",
      "rookie_year": 2017
    },
    "6721": {
      "name": "Tindley Trailblazers",
      "rookie_year": 2017
    },
    "6956": {
      "name": "SHAM-ROCK-BOTICS ☘",
      "rookie_year": 2018
    },
    "7198": {
      "name": "TL Fearsome Gears",
      "rookie_year": 2018
    },
    "7454": {
      "name": "Huskies on Hogs",
      "rookie_year": 2019
    },
    "7457": {
      "name": "suPURDUEper Robotics",
      "rookie_year": 2019
    },
    "7477": {
      "name": "Giddy GOATS",
      "rookie_year": 2019
    },
    "7617": {
      "name": "RoboBlazers",
      "rookie_year": 2019
    },
    "7657": {
      "name": "Thunderbots",
      "rookie_year": 2019
    },
    "7695": {
      "name": "Trojan Thunder",
      "rookie_year": 2019
    },
    "8103": {
      "name": "Knight Robotics",
      "rookie_year": 2020
    },
    "8116": {
      "name": "Hatchet Robotics",
      "rookie_year": 2020
    },
    "8232": {
      "name": "Girl Gang",
      "rookie_year": 2020
    },
    "8535": {
      "name": "The Lion Kings",
      "rookie_year": 2021
    },
    "8545": {
      "name": "Scott County Robotics",
      "rookie_year": 2021
    },
    "8564": {
      "name": "Disco Ducks",
      "rookie_year": 2021
    }
  },
  "championship": null
}